pyVies/__init__.py
pyVies/api.py
pyvieser-0.0.4.dist-info/AUTHORS
pyvieser-0.0.4.dist-info/LICENSE
pyvieser-0.0.4.dist-info/METADATA
pyvieser-0.0.4.dist-info/WHEEL
pyvieser-0.0.4.dist-info/entry_points.txt
pyvieser-0.0.4.dist-info/top_level.txt
pyvieser-0.0.4.dist-info/RECORD
